Algorithm/DFS.py
Algorithm/__init__.py
Math/Calculus.py
Math/Matrix.py
Math/Vector_space.py
Math/__init__.py
Math/linear_algebra.py
Password/__init__.py
Password/code.py
Structure/Stack.py
Structure/Tree.py
Structure/__init__.py
Utilities/__init__.py
Utilities/file_utiles.py
Utilities/logger.py
Utilities/math_utiles.py
tests/__init__.py
tests/conftest.py
tests/test_calculus.py
tests/test_dfs.py
tests/test_linear_algebra.py
tests/test_matrix.py
tests/test_stack.py
tests/test_tree.py
tests/test_vector_space.py
mathalgo-0.1.0.dist-info/LICENSE
mathalgo-0.1.0.dist-info/METADATA
mathalgo-0.1.0.dist-info/WHEEL
mathalgo-0.1.0.dist-info/top_level.txt
mathalgo-0.1.0.dist-info/RECORD
