Metadata-Version: 2.1
Name: mathalgo
Version: 0.1.0
Summary: MyMod 是一個專為 Python 開發者設計的模組，提供多種演算法、資料結構與數學工具，方便進行科學計算與程式開發。
Home-page: https://github.com/Donseking/MathAlgo
Author: Donseking
Author-email: Donseking <0717albert@gmail.com>
Project-URL: Homepage, https://github.com/Donseking/MathAlgo.git
Project-URL: Bug Tracker, https://github.com/Donseking/MathAlgo/issues
Classifier: Programming Language :: Python :: 3
Classifier: License :: OSI Approved :: MIT License
Classifier: Operating System :: OS Independent
Requires-Python: >=3.6
License-File: LICENSE
